[
 {
   "volume":0.1,
   "Tritanium":415,
   "Pyerite":0,
   "Mexallon":0,
   "Isogen":0,
   "Nocxium":0,
   "Zydrine":0,
   "Megacyte":0,
   "Morphite":0,
   "typeId":28432,
   "typeName":"Compressed Veldspar"
 },
 {
   "volume":0.1,
   "Tritanium":436,
   "Pyerite":0,
   "Mexallon":0,
   "Isogen":0,
   "Nocxium":0,
   "Zydrine":0,
   "Megacyte":0,
   "Morphite":0,
   "typeId":28430,
   "typeName":"Compressed Concentrated Veldspar"
 },
 {
   "volume":0.1,
   "Tritanium":457,
   "Pyerite":0,
   "Mexallon":0,
   "Isogen":0,
   "Nocxium":0,
   "Zydrine":0,
   "Megacyte":0,
   "Morphite":0,
   "typeId":28431,
   "typeName":"Compressed Dense Veldspar"
 },
 {
   "volume":0.15,
   "Tritanium":346,
   "Pyerite":173,
   "Mexallon":0,
   "Isogen":0,
   "Nocxium":0,
   "Zydrine":0,
   "Megacyte":0,
   "Morphite":0,
   "typeId":28429,
   "typeName":"Compressed Scordite"
 },
 {
   "volume":0.15,
   "Tritanium":364,
   "Pyerite":182,
   "Mexallon":0,
   "Isogen":0,
   "Nocxium":0,
   "Zydrine":0,
   "Megacyte":0,
   "Morphite":0,
   "typeId":28427,
   "typeName":"Compressed Condensed Scordite"
 },
 {
   "volume":0.15,
   "Tritanium":381,
   "Pyerite":190,
   "Mexallon":0,
   "Isogen":0,
   "Nocxium":0,
   "Zydrine":0,
   "Megacyte":0,
   "Morphite":0,
   "typeId":28428,
   "typeName":"Compressed Massive Scordite"
 },
 {
   "volume":0.3,
   "Tritanium":351,
   "Pyerite":25,
   "Mexallon":50,
   "Isogen":0,
   "Nocxium":5,
   "Zydrine":0,
   "Megacyte":0,
   "Morphite":0,
   "typeId":28424,
   "typeName":"Compressed Pyroxeres"
 },
 {
   "volume":0.3,
   "Tritanium":369,
   "Pyerite":26,
   "Mexallon":53,
   "Isogen":0,
   "Nocxium":5,
   "Zydrine":0,
   "Megacyte":0,
   "Morphite":0,
   "typeId":28425,
   "typeName":"Compressed Solid Pyroxeres"
 },
 {
   "volume":0.3,
   "Tritanium":387,
   "Pyerite":27,
   "Mexallon":55,
   "Isogen":0,
   "Nocxium":5,
   "Zydrine":0,
   "Megacyte":0,
   "Morphite":0,
   "typeId":28426,
   "typeName":"Compressed Viscous Pyroxeres"
 },
 {
   "volume":0.35,
   "Tritanium":107,
   "Pyerite":213,
   "Mexallon":107,
   "Isogen":0,
   "Nocxium":0,
   "Zydrine":0,
   "Megacyte":0,
   "Morphite":0,
   "typeId":28422,
   "typeName":"Compressed Plagioclase"
 },
 {
   "volume":0.35,
   "Tritanium":113,
   "Pyerite":224,
   "Mexallon":113,
   "Isogen":0,
   "Nocxium":0,
   "Zydrine":0,
   "Megacyte":0,
   "Morphite":0,
   "typeId":28421,
   "typeName":"Compressed Azure Plagioclase"
 },
 {
   "volume":0.35,
   "Tritanium":118,
   "Pyerite":235,
   "Mexallon":118,
   "Isogen":0,
   "Nocxium":0,
   "Zydrine":0,
   "Megacyte":0,
   "Morphite":0,
   "typeId":28423,
   "typeName":"Compressed Rich Plagioclase"
 },
 {
   "volume":0.6,
   "Tritanium":800,
   "Pyerite":100,
   "Mexallon":0,
   "Isogen":85,
   "Nocxium":0,
   "Zydrine":0,
   "Megacyte":0,
   "Morphite":0,
   "typeId":28416,
   "typeName":"Compressed Omber"
 },
 {
   "volume":0.6,
   "Tritanium":840,
   "Pyerite":105,
   "Mexallon":0,
   "Isogen":90,
   "Nocxium":0,
   "Zydrine":0,
   "Megacyte":0,
   "Morphite":0,
   "typeId":28417,
   "typeName":"Compressed Silvery Omber"
 },
 {
   "volume":0.6,
   "Tritanium":880,
   "Pyerite":110,
   "Mexallon":0,
   "Isogen":94,
   "Nocxium":0,
   "Zydrine":0,
   "Megacyte":0,
   "Morphite":0,
   "typeId":28415,
   "typeName":"Compressed Golden Omber"
 },
 {
   "volume":1.2,
   "Tritanium":134,
   "Pyerite":0,
   "Mexallon":267,
   "Isogen":134,
   "Nocxium":0,
   "Zydrine":0,
   "Megacyte":0,
   "Morphite":0,
   "typeId":28410,
   "typeName":"Compressed Kernite"
 },
 {
   "volume":1.2,
   "Tritanium":141,
   "Pyerite":0,
   "Mexallon":281,
   "Isogen":141,
   "Nocxium":0,
   "Zydrine":0,
   "Megacyte":0,
   "Morphite":0,
   "typeId":28411,
   "typeName":"Compressed Luminous Kernite"
 },
 {
   "volume":1.2,
   "Tritanium":148,
   "Pyerite":0,
   "Mexallon":294,
   "Isogen":148,
   "Nocxium":0,
   "Zydrine":0,
   "Megacyte":0,
   "Morphite":0,
   "typeId":28409,
   "typeName":"Compressed Fiery Kernite"
 },
 {
   "volume":2,
   "Tritanium":0,
   "Pyerite":0,
   "Mexallon":350,
   "Isogen":0,
   "Nocxium":75,
   "Zydrine":8,
   "Megacyte":0,
   "Morphite":0,
   "typeId":28406,
   "typeName":"Compressed Jaspet"
 },
 {
   "volume":2,
   "Tritanium":0,
   "Pyerite":0,
   "Mexallon":368,
   "Isogen":0,
   "Nocxium":79,
   "Zydrine":8,
   "Megacyte":0,
   "Morphite":0,
   "typeId":28408,
   "typeName":"Compressed Pure Jaspet"
 },
 {
   "volume":2,
   "Tritanium":0,
   "Pyerite":0,
   "Mexallon":385,
   "Isogen":0,
   "Nocxium":83,
   "Zydrine":9,
   "Megacyte":0,
   "Morphite":0,
   "typeId":28407,
   "typeName":"Compressed Pristine Jaspet"
 },
 {
   "volume":3,
   "Tritanium":2200,
   "Pyerite":0,
   "Mexallon":0,
   "Isogen":100,
   "Nocxium":120,
   "Zydrine":15,
   "Megacyte":0,
   "Morphite":0,
   "typeId":28403,
   "typeName":"Compressed Hemorphite"
 },
 {
   "volume":3,
   "Tritanium":2310,
   "Pyerite":0,
   "Mexallon":0,
   "Isogen":105,
   "Nocxium":126,
   "Zydrine":16,
   "Megacyte":0,
   "Morphite":0,
   "typeId":28405,
   "typeName":"Compressed Vivid Hemorphite"
 },
 {
   "volume":3,
   "Tritanium":2420,
   "Pyerite":0,
   "Mexallon":0,
   "Isogen":110,
   "Nocxium":132,
   "Zydrine":17,
   "Megacyte":0,
   "Morphite":0,
   "typeId":28404,
   "typeName":"Compressed Radiant Hemorphite"
 },
 {
   "volume":3,
   "Tritanium":0,
   "Pyerite":1000,
   "Mexallon":0,
   "Isogen":200,
   "Nocxium":100,
   "Zydrine":19,
   "Megacyte":0,
   "Morphite":0,
   "typeId":28401,
   "typeName":"Compressed Hedbergite"
 },
 {
   "volume":3,
   "Tritanium":0,
   "Pyerite":1050,
   "Mexallon":0,
   "Isogen":210,
   "Nocxium":105,
   "Zydrine":20,
   "Megacyte":0,
   "Morphite":0,
   "typeId":28402,
   "typeName":"Compressed Vitric Hedbergite"
 },
 {
   "volume":3,
   "Tritanium":0,
   "Pyerite":1100,
   "Mexallon":0,
   "Isogen":220,
   "Nocxium":110,
   "Zydrine":21,
   "Megacyte":0,
   "Morphite":0,
   "typeId":28400,
   "typeName":"Compressed Glazed Hedbergite"
 },
 {
   "volume":5,
   "Tritanium":0,
   "Pyerite":2200,
   "Mexallon":2400,
   "Isogen":300,
   "Nocxium":0,
   "Zydrine":0,
   "Megacyte":0,
   "Morphite":0,
   "typeId":28397,
   "typeName":"Compressed Gneiss"
 },
 {
   "volume":5,
   "Tritanium":0,
   "Pyerite":2310,
   "Mexallon":2520,
   "Isogen":315,
   "Nocxium":0,
   "Zydrine":0,
   "Megacyte":0,
   "Morphite":0,
   "typeId":28398,
   "typeName":"Compressed Iridescent Gneiss"
 },
 {
   "volume":5,
   "Tritanium":0,
   "Pyerite":2420,
   "Mexallon":2640,
   "Isogen":330,
   "Nocxium":0,
   "Zydrine":0,
   "Megacyte":0,
   "Morphite":0,
   "typeId":28399,
   "typeName":"Compressed Prismatic Gneiss"
 },
 {
   "volume":8,
   "Tritanium":10000,
   "Pyerite":0,
   "Mexallon":0,
   "Isogen":1600,
   "Nocxium":120,
   "Zydrine":0,
   "Megacyte":0,
   "Morphite":0,
   "typeId":28394,
   "typeName":"Compressed Dark Ochre"
 },
 {
   "volume":8,
   "Tritanium":10500,
   "Pyerite":0,
   "Mexallon":0,
   "Isogen":1680,
   "Nocxium":126,
   "Zydrine":0,
   "Megacyte":0,
   "Morphite":0,
   "typeId":28396,
   "typeName":"Compressed Onyx Ochre"
 },
 {
   "volume":8,
   "Tritanium":11000,
   "Pyerite":0,
   "Mexallon":0,
   "Isogen":1760,
   "Nocxium":132,
   "Zydrine":0,
   "Megacyte":0,
   "Morphite":0,
   "typeId":28395,
   "typeName":"Compressed Obsidian Ochre"
 },
 {
   "volume":16,
   "Tritanium":56000,
   "Pyerite":12050,
   "Mexallon":2100,
   "Isogen":450,
   "Nocxium":0,
   "Zydrine":0,
   "Megacyte":0,
   "Morphite":0,
   "typeId":28420,
   "typeName":"Compressed Spodumain"
 },
 {
   "volume":16,
   "Tritanium":58800,
   "Pyerite":12653,
   "Mexallon":2205,
   "Isogen":473,
   "Nocxium":0,
   "Zydrine":0,
   "Megacyte":0,
   "Morphite":0,
   "typeId":28418,
   "typeName":"Compressed Bright Spodumain"
 },
 {
   "volume":16,
   "Tritanium":61600,
   "Pyerite":13255,
   "Mexallon":2310,
   "Isogen":495,
   "Nocxium":0,
   "Zydrine":0,
   "Megacyte":0,
   "Morphite":0,
   "typeId":28419,
   "typeName":"Compressed Gleaming Spodumain"
 },
 {
   "volume":16,
   "Tritanium":21000,
   "Pyerite":0,
   "Mexallon":0,
   "Isogen":0,
   "Nocxium":760,
   "Zydrine":135,
   "Megacyte":0,
   "Morphite":0,
   "typeId":28391,
   "typeName":"Compressed Crokite"
 },
 {
   "volume":16,
   "Tritanium":22050,
   "Pyerite":0,
   "Mexallon":0,
   "Isogen":0,
   "Nocxium":798,
   "Zydrine":142,
   "Megacyte":0,
   "Morphite":0,
   "typeId":28393,
   "typeName":"Compressed Sharp Crokite"
 },
 {
   "volume":16,
   "Tritanium":23100,
   "Pyerite":0,
   "Mexallon":0,
   "Isogen":0,
   "Nocxium":836,
   "Zydrine":149,
   "Megacyte":0,
   "Morphite":0,
   "typeId":28392,
   "typeName":"Compressed Crystalline Crokite"
 },
 {
   "volume":16,
   "Tritanium":0,
   "Pyerite":12000,
   "Mexallon":0,
   "Isogen":0,
   "Nocxium":0,
   "Zydrine":450,
   "Megacyte":100,
   "Morphite":0,
   "typeId":28388,
   "typeName":"Compressed Bistot"
 },
 {
   "volume":16,
   "Tritanium":0,
   "Pyerite":12600,
   "Mexallon":0,
   "Isogen":0,
   "Nocxium":0,
   "Zydrine":473,
   "Megacyte":105,
   "Morphite":0,
   "typeId":28390,
   "typeName":"Compressed Triclinic Bistot"
 },
 {
   "volume":16,
   "Tritanium":0,
   "Pyerite":13200,
   "Mexallon":0,
   "Isogen":0,
   "Nocxium":0,
   "Zydrine":495,
   "Megacyte":110,
   "Morphite":0,
   "typeId":28389,
   "typeName":"Compressed Monoclinic Bistot"
 },
 {
   "volume":16,
   "Tritanium":22000,
   "Pyerite":0,
   "Mexallon":2500,
   "Isogen":0,
   "Nocxium":0,
   "Zydrine":0,
   "Megacyte":320,
   "Morphite":0,
   "typeId":28367,
   "typeName":"Compressed Arkonor"
 },
 {
   "volume":16,
   "Tritanium":23100,
   "Pyerite":0,
   "Mexallon":2625,
   "Isogen":0,
   "Nocxium":0,
   "Zydrine":0,
   "Megacyte":336,
   "Morphite":0,
   "typeId":28385,
   "typeName":"Compressed Crimson Arkonor"
 },
 {
   "volume":16,
   "Tritanium":24200,
   "Pyerite":0,
   "Mexallon":2750,
   "Isogen":0,
   "Nocxium":0,
   "Zydrine":0,
   "Megacyte":352,
   "Morphite":0,
   "typeId":28387,
   "typeName":"Compressed Prime Arkonor"
 },
 {
   "volume":40,
   "Tritanium":0,
   "Pyerite":0,
   "Mexallon":0,
   "Isogen":0,
   "Nocxium":0,
   "Zydrine":0,
   "Megacyte":0,
   "Morphite":300,
   "typeId":28413,
   "typeName":"Compressed Mercoxit"
 },
 {
   "volume":40,
   "Tritanium":0,
   "Pyerite":0,
   "Mexallon":0,
   "Isogen":0,
   "Nocxium":0,
   "Zydrine":0,
   "Megacyte":0,
   "Morphite":315,
   "typeId":28412,
   "typeName":"Compressed Magma Mercoxit"
 },
 {
   "volume":40,
   "Tritanium":0,
   "Pyerite":0,
   "Mexallon":0,
   "Isogen":0,
   "Nocxium":0,
   "Zydrine":0,
   "Megacyte":0,
   "Morphite":330,
   "typeId":28414,
   "typeName":"Compressed Vitreous Mercoxit"
 }
]